ocrbridge/__init__.py
ocrbridge/engines/__init__.py
ocrbridge/engines/tesseract/__init__.py
ocrbridge/engines/tesseract/engine.py
ocrbridge/engines/tesseract/models.py
ocrbridge_tesseract-3.0.1.dist-info/METADATA
ocrbridge_tesseract-3.0.1.dist-info/WHEEL
ocrbridge_tesseract-3.0.1.dist-info/entry_points.txt
ocrbridge_tesseract-3.0.1.dist-info/licenses/LICENSE
ocrbridge_tesseract-3.0.1.dist-info/RECORD
