Metadata-Version: 2.4
Name: ocrbridge-tesseract
Version: 3.0.1
Summary: Tesseract OCR engine for OCR Bridge
License: MIT
License-File: LICENSE
Requires-Python: >=3.10
Requires-Dist: ocrbridge-core>=3.1.0
Requires-Dist: pillow>=10.0.0
Requires-Dist: pydantic>=2.0
Requires-Dist: pytesseract>=0.3.13
Provides-Extra: build
Requires-Dist: python-semantic-release>=10.5.2; extra == 'build'
Provides-Extra: test
Requires-Dist: pytest~=9.0; extra == 'test'
